ethos/__init__.py
ethos/argparser.py
ethos/config.py
ethos/main.py
ethos/player.py
ethos/spotify_importer.py
ethos/tools/__init__.py
ethos/tools/endless_playback.py
ethos/tools/helper.py
ethos/ui/__init__.py
ethos/ui/rich_layout.py
ethos/ui/styles.tcss
ethos/ui/textual_app.py
ethos/ui/ui.py
ethos/ui/utils/assets.py
ethos/ui/utils/square_drawer.py
ethos/utils.py
ethos_cli-0.1.0.dist-info/entry_points.txt
ethos_cli-0.1.0.dist-info/LICENSE
ethos_cli-0.1.0.dist-info/METADATA
ethos_cli-0.1.0.dist-info/WHEEL
ethos_cli-0.1.0.dist-info/RECORD
