Metadata-Version: 2.3
Name: ethos-cli
Version: 0.1.0
Summary: A cross-platform CLI music player delivering local and online music streaming with User's Spotify playlist integration.
License: MIT
Keywords: ethos,cli-music-player,spotify,vlc,yt-dlp,audio-player
Author: Agasta
Author-email: rupam.golui@proton.me
Maintainer: Agasta
Maintainer-email: rupam.golui@proton.me
Requires-Python: >=3.9,<4.0
Classifier: Development Status :: 4 - Beta
Classifier: Environment :: Console
Classifier: Intended Audience :: End Users/Desktop
Classifier: License :: OSI Approved :: MIT License
Classifier: Operating System :: OS Independent
Classifier: Programming Language :: Python :: 3
Classifier: Programming Language :: Python :: 3.9
Classifier: Programming Language :: Python :: 3.10
Classifier: Programming Language :: Python :: 3.11
Classifier: Programming Language :: Python :: 3.12
Classifier: Programming Language :: Python :: 3.13
Classifier: Topic :: Multimedia :: Sound/Audio :: Players
Requires-Dist: httpx (>=0.28.1)
Requires-Dist: python-dotenv (==1.0.1)
Requires-Dist: python-vlc (==3.0.21203)
Requires-Dist: rich (==13.9.4)
Requires-Dist: spotipy (==2.25.0)
Requires-Dist: textual (==1.0.0)
Requires-Dist: yt-dlp (==2025.01.26)
Project-URL: documentation, https://github.com/Itz-Agasta/ethos/blob/master/README.md
Project-URL: homepage, https://github.com/Itz-Agasta/ethos
Project-URL: repository, https://github.com/Itz-Agasta/ethos
